[{"Predicted Rank": 1, "Player Name": "Jon Rahm", "Win %": 17.27, "Fair Odds": 5.79}, {"Predicted Rank": 2, "Player Name": "Dustin Johnson", "Win %": 16.77, "Fair Odds": 5.96}, {"Predicted Rank": 3, "Player Name": "Justin Thomas", "Win %": 9.69, "Fair Odds": 10.32}, {"Predicted Rank": 4, "Player Name": "Xander Schauffele", "Win %": 7.32, "Fair Odds": 13.66}, {"Predicted Rank": 5, "Player Name": "Webb Simpson", "Win %": 6.78, "Fair Odds": 14.75}, {"Predicted Rank": 6, "Player Name": "Rory McIlroy", "Win %": 5.04, "Fair Odds": 19.84}, {"Predicted Rank": 7, "Player Name": "Hideki Matsuyama", "Win %": 4.49, "Fair Odds": 22.27}, {"Predicted Rank": 8, "Player Name": "Bryson DeChambeau", "Win %": 3.73, "Fair Odds": 26.81}, {"Predicted Rank": 9, "Player Name": "Collin Morikawa", "Win %": 3.73, "Fair Odds": 26.81}, {"Predicted Rank": 10, "Player Name": "Daniel Berger", "Win %": 3.52, "Fair Odds": 28.41}, {"Predicted Rank": 11, "Player Name": "Tony Finau", "Win %": 2.27, "Fair Odds": 44.05}, {"Predicted Rank": 12, "Player Name": "Tyrrell Hatton", "Win %": 2.13, "Fair Odds": 46.95}, {"Predicted Rank": 13, "Player Name": "Scottie Scheffler", "Win %": 2.1, "Fair Odds": 47.62}, {"Predicted Rank": 14, "Player Name": "Patrick Reed", "Win %": 1.97, "Fair Odds": 50.76}, {"Predicted Rank": 15, "Player Name": "Harris English", "Win %": 1.54, "Fair Odds": 64.94}, {"Predicted Rank": 16, "Player Name": "Viktor Hovland", "Win %": 1.5, "Fair Odds": 66.67}, {"Predicted Rank": 17, "Player Name": "Billy Horschel", "Win %": 1.26, "Fair Odds": 79.37}, {"Predicted Rank": 18, "Player Name": "Abraham Ancer", "Win %": 1.17, "Fair Odds": 85.47}, {"Predicted Rank": 19, "Player Name": "Joaquin Niemann", "Win %": 1.08, "Fair Odds": 92.59}, {"Predicted Rank": 20, "Player Name": "Kevin Kisner", "Win %": 0.99, "Fair Odds": 101.01}, {"Predicted Rank": 21, "Player Name": "Sungjae Im", "Win %": 0.9, "Fair Odds": 111.11}, {"Predicted Rank": 22, "Player Name": "Brendon Todd", "Win %": 0.73, "Fair Odds": 136.99}, {"Predicted Rank": 23, "Player Name": "Ryan Palmer", "Win %": 0.67, "Fair Odds": 149.25}, {"Predicted Rank": 24, "Player Name": "Kevin Na", "Win %": 0.63, "Fair Odds": 158.73}, {"Predicted Rank": 25, "Player Name": "Lanto Griffin", "Win %": 0.57, "Fair Odds": 175.44}, {"Predicted Rank": 26, "Player Name": "Sebasti\u00e1n Mu\u00f1oz", "Win %": 0.54, "Fair Odds": 185.19}, {"Predicted Rank": 27, "Player Name": "Cameron Smith", "Win %": 0.51, "Fair Odds": 196.08}, {"Predicted Rank": 28, "Player Name": "Mackenzie Hughes", "Win %": 0.49, "Fair Odds": 204.08}, {"Predicted Rank": 29, "Player Name": "Marc Leishman", "Win %": 0.33, "Fair Odds": 303.03}, {"Predicted Rank": 30, "Player Name": "Cameron Champ", "Win %": 0.27, "Fair Odds": 370.37}]