[{"name": "Novak Djokovic", "data": [{"t": 1618271290507, "y": 40.82}, {"t": 1618272090955, "y": 40.82}, {"t": 1618272760808, "y": 40.82}]}, {"name": "Dominic Thiem", "data": [{"t": 1618271290507, "y": 13.16}, {"t": 1618272090955, "y": 13.16}, {"t": 1618272760808, "y": 13.16}]}, {"name": "Daniil Medvedev", "data": [{"t": 1618271290507, "y": 8.13}, {"t": 1618272090955, "y": 8.13}, {"t": 1618272760808, "y": 8.13}]}, {"name": "Rafael Nadal", "data": [{"t": 1618271290507, "y": 9.26}, {"t": 1618272090955, "y": 9.26}, {"t": 1618272760808, "y": 9.26}]}, {"name": "Alexander Zverev", "data": [{"t": 1618271290507, "y": 5.33}, {"t": 1618272090955, "y": 5.33}, {"t": 1618272760808, "y": 5.33}]}, {"name": "Stefanos Tsitsipas", "data": [{"t": 1618271290507, "y": 5.06}, {"t": 1618272090955, "y": 5.06}, {"t": 1618272760808, "y": 5.06}]}, {"name": "Roger Federer", "data": [{"t": 1618271290507, "y": 2.3}, {"t": 1618272090955, "y": 2.3}, {"t": 1618272760808, "y": 2.3}]}, {"name": "Andrey Rublev", "data": [{"t": 1618271290507, "y": 3.39}, {"t": 1618272090955, "y": 3.39}, {"t": 1618272760808, "y": 3.39}]}, {"name": "Jannik Sinner", "data": [{"t": 1618271290507, "y": 3.17}, {"t": 1618272090955, "y": 3.17}, {"t": 1618272760808, "y": 3.17}]}, {"name": "Aslan Karatsev", "data": [{"t": 1618271290507, "y": 2.25}, {"t": 1618272090955, "y": 2.25}, {"t": 1618272760808, "y": 2.25}]}, {"name": "Milos Raonic", "data": [{"t": 1618271290507, "y": 0.6}, {"t": 1618272090955, "y": 0.6}, {"t": 1618272760808, "y": 0.6}]}, {"name": "Denis Shapovalov", "data": [{"t": 1618271290507, "y": 0.82}, {"t": 1618272090955, "y": 0.82}, {"t": 1618272760808, "y": 0.82}]}, {"name": "Nick Kyrgios", "data": [{"t": 1618271290507, "y": 0.33}, {"t": 1618272090955, "y": 0.33}, {"t": 1618272760808, "y": 0.33}]}, {"name": "Stan Wawrinka", "data": [{"t": 1618271290507, "y": 0.56}, {"t": 1618272090955, "y": 0.56}, {"t": 1618272760808, "y": 0.56}]}, {"name": "Alex De Minaur", "data": [{"t": 1618271290507, "y": 0.54}, {"t": 1618272090955, "y": 0.54}, {"t": 1618272760808, "y": 0.54}]}, {"name": "Grigor Dimitrov", "data": [{"t": 1618271290507, "y": 0.32}, {"t": 1618272090955, "y": 0.32}, {"t": 1618272760808, "y": 0.32}]}, {"name": "Karen Khachanov", "data": [{"t": 1618271290507, "y": 0.35}, {"t": 1618272090955, "y": 0.35}, {"t": 1618272760808, "y": 0.35}]}, {"name": "Matteo Berrettini", "data": [{"t": 1618271290507, "y": 0.77}, {"t": 1618272090955, "y": 0.77}, {"t": 1618272760808, "y": 0.77}]}, {"name": "Pablo Carreno Busta", "data": [{"t": 1618271290507, "y": 0.25}, {"t": 1618272090955, "y": 0.25}, {"t": 1618272760808, "y": 0.25}]}, {"name": "Felix Auger-Aliassime", "data": [{"t": 1618271290507, "y": 0.43}, {"t": 1618272090955, "y": 0.43}, {"t": 1618272760808, "y": 0.43}]}, {"name": "Daniel Evans", "data": [{"t": 1618271290507, "y": 0.18}, {"t": 1618272090955, "y": 0.18}, {"t": 1618272760808, "y": 0.18}]}, {"name": "David Goffin", "data": [{"t": 1618271290507, "y": 0.22}, {"t": 1618272090955, "y": 0.22}, {"t": 1618272760808, "y": 0.22}]}, {"name": "Gael Monfils", "data": [{"t": 1618271290507, "y": 0.18}, {"t": 1618272090955, "y": 0.18}, {"t": 1618272760808, "y": 0.18}]}, {"name": "Diego Schwartzman", "data": [{"t": 1618271290507, "y": 0.28}, {"t": 1618272090955, "y": 0.28}, {"t": 1618272760808, "y": 0.28}]}, {"name": "Fabio Fognini", "data": [{"t": 1618271290507, "y": 0.17}, {"t": 1618272090955, "y": 0.17}, {"t": 1618272760808, "y": 0.17}]}, {"name": "Kyle Edmund", "data": [{"t": 1618271290507, "y": 0.16}, {"t": 1618272090955, "y": 0.16}, {"t": 1618272760808, "y": 0.16}]}]